{"time":{"updated":"Jul 25, 2020 00:12:00 UTC","updatedISO":"2020-07-25T00:12:00+00:00","updateduk":"Jul 25, 2020 at 01:12 BST"},"disclaimer":"This data was produced from the CoinDesk Bitcoin Price Index (USD). Non-USD currency data converted using hourly conversion rate from openexchangerates.org","chartName":"Bitcoin","bpi":{"USD":{"code":"USD","symbol":"&#36;","rate":"9,558.4083","description":"United States Dollar","rate_float":9558.4083},"GBP":{"code":"GBP","symbol":"&pound;","rate":"7,499.6131","description":"British Pound Sterling","rate_float":7499.6131},"EUR":{"code":"EUR","symbol":"&euro;","rate":"8,230.6784","description":"Euro","rate_float":8230.6784}}}
